[
    {
        "typeName": "player",
        "animated": true,
        "sprite": {
            "path": "images/player.sf",
            "origin": {
                "x": 26,
                "y": 65
            }
        },
        "handler": "ActorHandler"
    },
    {
        "typeName": "enemy",
        "animated": true,
        "sprite": {
            "path": "images/enemy.sf",
            "origin": {
                "x": 26,
                "y": 65
            }
        },
        "handler": "ActorHandler"
    },
    {
        "typeName": "chest1",
        "animated": true,
        "sprite": {
            "path": "images/chest1.sf",
            "origin": {
                "x": 16,
                "y": 20
            }
        },
        "handler": "ChestHandler"
    },
    {
        "typeName": "blue_potion1",
        "stackSize": 10,
        "flags": 1,
        "sprite": {
            "path": "images/dragons_blade",
            "region": {
                "x": 224,
                "y": 0,
                "width": 32,
                "height": 32
            }
        }
    },
    {
        "typeName": "red_potion1",
        "stackSize": 10,
        "flags": 1,
        "sprite": {
            "path": "images/dragons_blade",
            "region": {
                "x": 192,
                "y": 0,
                "width": 32,
                "height": 32
            }
        }
    },
    {
        "typeName": "gladius1",
        "stackSize": 1,
        "flags": 20,
        "sprite": {
            "path": "images/dragons_blade_2",
            "region": {
                "x": 96,
                "y": 0,
                "width": 32,
                "height": 32
            }
        }
    },
    {
        "typeName": "helmet1",
        "flags": 10,
        "stackSize": 1,
        "sprite": {
            "path": "images/dragons_blade_2",
            "region": {
                "x": 64,
                "y": 64,
                "width": 32,
                "height": 32
            }
        }
    }
]